plotdelice/__init__.py
plotdelice/graphs.py
plotdelice/stats.py
PlotDelice-0.5.dist-info/METADATA
PlotDelice-0.5.dist-info/WHEEL
PlotDelice-0.5.dist-info/top_level.txt
PlotDelice-0.5.dist-info/RECORD
