Metadata-Version: 2.1
Name: PlotDelice
Version: 0.5
Summary: A package for creating old school style plots
Home-page: https://github.com/daggermaster3000/plotdelice
Author: Quillan Favey
Author-email: quillan.favey@gmail.com
Classifier: Programming Language :: Python :: 3
Classifier: License :: OSI Approved :: MIT License
Classifier: Operating System :: OS Independent
Requires-Python: >=3.6
Requires-Dist: numpy
Requires-Dist: pandas
Requires-Dist: matplotlib
Requires-Dist: seaborn
Requires-Dist: scipy
Requires-Dist: statsmodels
